{
    "data": [
        {
          "source_language_code": "en",
          "target_language_code": "bn",
          "model_id": 11,
          "model_name": "model no-1:",
          "is_primary": true,
          "created_on": "2019-09-16T12:07:52.645Z",
          "status": "ACTIVE",
          "source_language_name":"English",
          "target_language_name":"Bengali"
        },
        {
          "source_language_code": "en",
          "target_language_code": "mr",
          "model_id": 12,
          "model_name": "model no-1:",
          "is_primary": false,
          "created_on": "2019-09-16T12:08:47.726Z",
          "status": "INACTIVE",
          "source_language_name":"English",
          "target_language_name":"Marathi"
        },
        {
          "source_language_code": "en",
          "target_language_code": "gu",
          "model_id": 10,
          "model_name": "model no-1:",
          "is_primary": true,
          "created_on": "2019-09-16T12:12:21.750Z",
          "status": "ACTIVE",
          "source_language_name":"English",
          "target_language_name":"Gujarati"
        },
        {
          "source_language_code": "en",
          "target_language_code": "ta",
          "model_id": 7,
          "model_name": "model no-2:",
          "is_primary": true,
          "created_on": "2019-09-16T12:14:26.974Z",
          "status": "ACTIVE",
          "source_language_name":"English",
          "target_language_name":"Tamil"
        },
        {
          "source_language_code": "en",
          "target_language_code": "kn",
          "model_id": 15,
          "model_name": "model-kannda-1-100k",
          "is_primary": true,
          "created_on": "2019-09-22T13:42:24.099Z",
          "status": "ACTIVE",
          "source_language_name":"English",
          "target_language_name":"Kannada"
        },
        {
          "source_language_code": "en",
          "target_language_code": "te",
          "model_id": 16,
          "model_name": "modeltelgu-1-100k",
          "is_primary": true,
          "created_on": "2019-09-22T13:42:52.058Z",
          "status": "ACTIVE",
          "source_language_name":"English",
          "target_language_name":"Telugu"
        },
        {
          "source_language_code": "en",
          "target_language_code": "ml",
          "model_id": 17,
          "model_name": "model-malayalam-1-100k",
          "is_primary": true,
          "created_on": "2019-09-22T13:43:27.726Z",
          "status": "ACTIVE",
          "source_language_name":"English",
          "target_language_name":"Malayalam"
        },
        {
          "source_language_code": "en",
          "target_language_code": "pa",
          "model_id": 18,
          "model_name": "model-punjabi-1-80k",
          "is_primary": true,
          "created_on": "2019-09-22T13:44:16.761Z",
          "status": "ACTIVE",
          "source_language_name":"English",
          "target_language_name":"Punjabi"
        },
        {
          "source_language_code": "en",
          "target_language_code": "hi",
          "model_id": 21,
          "model_name": "Model_experiment_1",
          "is_primary": false,
          "description": "BPE model with varying vocab size 15k for both hindi and english,Orders data augmented,pre_tokenization",
          "created_on": "2019-10-07T10:58:10.331Z",
          "status": "INACTIVE",
          "source_language_name":"English",
          "target_language_name":"Hindi"
        },
        {
          "source_language_code": "en",
          "target_language_code": "hi",
          "model_id": 54,
          "model_name": "Model_experiment_5.4(BPE-24K)",
          "is_primary": false,
          "description": "BPE-24K, Old data+ india kanoon 800k(including 1.5 lakhs names,no learned_counsel)+74k shabkosh,50knmt",
          "created_on": "2019-10-31T15:55:43.084Z",
          "status": "INACTIVE",
          "source_language_name":"English",
          "target_language_name":"Hindi"
        },
        {
          "source_language_code": "en",
          "target_language_code": "hi",
          "model_id": 32,
          "model_name": "Model_experiment_12(formal++)",
          "is_primary": false,
          "description": "old_data_original+lc_cleaned+ ik names translated from google(100k)+shabdkosh(appended 29k new),BPE-24K,50knmt,shuff,pretok",
          "created_on": "2019-10-31T15:57:17.667Z",
          "status": "ACTIVE",
          "source_language_name":"English",
          "target_language_name":"Hindi"
        },
        {
          "source_language_code": "hi",
          "target_language_code": "en",
          "model_id": 5,
          "model_name": "Model_experiment_1(BPE-24K)",
          "is_primary": false,
          "description": "old_data_original+lc_cleaned, shabdkosh(appended 29k new),BPE-24K,50knmt,shuff,pretok",
          "created_on": "2019-10-31T22:12:13.548Z",
          "status": "ACTIVE",
          "source_language_name":"Hindi",
          "target_language_name":"English"
        },
        {
          "source_language_code": "en",
          "target_language_code": "mr",
          "model_id": 42,
          "model_name": "Model_experiment_2(BPE-24K)",
          "is_primary": true,
          "description": "india_kanoon 8.5l cleaned,shabkosh,orders curated,BPE-24K,50knmt,shuff,pretok",
          "created_on": "2019-11-08T10:54:27.788Z",
          "status": "ACTIVE",
          "source_language_name":"English",
          "target_language_name":"Marathi"
        },
        {
          "source_language_code": "en",
          "target_language_code": "hi",
          "model_id": 56,
          "model_name": "Model_experiment_5.6",
          "is_primary": true,
          "description": "Built over 5.4 and 5.5 model with manually curated data. BPE-24K, IITB data + india kanoon data +74k shabkosh",
          "created_on": "2019-12-12T06:04:35.221Z",
          "status": "ACTIVE",
          "source_language_name":"English",
          "target_language_name":"Hindi"
        },
        {
          "source_language_code": "ta",
          "target_language_code": "en",
          "model_id": 8,
          "model_name": "Tamil-Eng Model-1",
          "is_primary": true,
          "description": "",
          "created_on": "2020-01-12T06:30:46.982Z",
          "status": "ACTIVE",
          "source_language_name":"Tamil",
          "target_language_name":"English"
        },
        {
          "source_language_code": "mr",
          "target_language_code": "en",
          "model_id": 43,
          "model_name": "Marathi-Eng Model-1",
          "is_primary": false,
          "description": "On newly tokenized IK corpus 10.5 lakhs",
          "created_on": "2020-01-29T11:25:48.822Z",
          "status": "INACTIVE",
          "source_language_name":"Marathi",
          "target_language_name":"English"
        },
        {
          "source_language_code": "en",
          "target_language_code": "mr",
          "model_id": 44,
          "model_name": "Eng-Mr Model-3",
          "is_primary": false,
          "description": "On newly tokenized IK corpus 10.5 lakhs",
          "created_on": "2020-02-10T06:51:39.501Z",
          "status": "ACTIVE",
          "source_language_name":"English",
          "target_language_name":"Marathi"
        },
        {
          "source_language_code": "en",
          "target_language_code": "ta",
          "model_id": 45,
          "model_name": "Eng-Tamil Model-4",
          "is_primary": false,
          "description": "On newly tokenized IK corpus 1.1 Million",
          "created_on": "2020-02-10T06:53:00.784Z",
          "status": "ACTIVE",
          "source_language_name":"English",
          "target_language_name":"Tamil"
        },
        {
          "source_language_code": "ta",
          "target_language_code": "en",
          "model_id": 46,
          "model_name": "Tamil-Eng Model-2",
          "is_primary": false,
          "description": "On newly tokenized IK corpus 1.1 Million",
          "created_on": "2020-02-13T06:10:43.377Z",
          "status": "INACTIVE",
          "source_language_name":"Tamil",
          "target_language_name":"English"
        },
        {
          "source_language_code": "kn",
          "target_language_code": "en",
          "model_id": 48,
          "model_name": "Kannada-Eng Model-1",
          "is_primary": true,
          "description": "On newly tokenized IK(v-3) corpus 1.2 Million",
          "created_on": "2020-02-13T06:12:17.608Z",
          "status": "ACTIVE",
          "source_language_name":"Kannada",
          "target_language_name":"English"
        },
        {
          "source_language_code": "en",
          "target_language_code": "kn",
          "model_id": 47,
          "model_name": "English-Kannada Model-2",
          "is_primary": false,
          "description": "On newly tokenized IK(v-3) corpus 1.2 Million",
          "created_on": "2020-02-13T06:13:05.895Z",
          "status": "ACTIVE",
          "source_language_name":"English",
          "target_language_name":"Kannada"
        },
        {
          "source_language_code": "en",
          "target_language_code": "te",
          "model_id": 49,
          "model_name": "English-Telugu Model-2",
          "is_primary": false,
          "description": "On newly tokenized IK(v-3) corpus 1.1 Million",
          "created_on": "2020-02-17T06:37:17.248Z",
          "status": "ACTIVE",
          "source_language_name":"English",
          "target_language_name":"Telugu"
        },
        {
          "source_language_code": "te",
          "target_language_code": "en",
          "model_id": 50,
          "model_name": "Telugu-English Model-1",
          "is_primary": true,
          "description": "On newly tokenized IK(v-3) corpus 1.1 Million",
          "created_on": "2020-02-17T06:37:53.636Z",
          "status": "ACTIVE",
          "source_language_name":"Telugu",
          "target_language_name":"English"
        },
        {
          "source_language_code": "en",
          "target_language_code": "gu",
          "model_id": 51,
          "model_name": "English-Gujarati Model-2",
          "is_primary": false,
          "description": "On newly tokenized IK(v-3) corpus 1.1 Million",
          "created_on": "2020-02-17T06:39:05.429Z",
          "status": "ACTIVE",
          "source_language_name":"English",
          "target_language_name":"Gujarati"
        },
        {
          "source_language_code": "gu",
          "target_language_code": "en",
          "model_id": 52,
          "model_name": "Gujarati-English Model-1",
          "is_primary": true,
          "description": "On newly tokenized IK(v-3) corpus 1.1 Million",
          "created_on": "2020-02-17T06:40:01.119Z",
          "status": "ACTIVE",
          "source_language_name":"Gujarati",
          "target_language_name":"English"
        },
        {
          "source_language_code": "en",
          "target_language_code": "pa",
          "model_id": 53,
          "model_name": "English-Punjabi Model-2",
          "is_primary": false,
          "description": "On newly tokenized IK(v-3) corpus 1.1 Million",
          "created_on": "2020-02-19T06:03:19.162Z",
          "status": "ACTIVE",
          "source_language_name":"English",
          "target_language_name":"Punjabi"
        },
        {
          "source_language_code": "pa",
          "target_language_code": "en",
          "model_id": 55,
          "model_name": "Punjabi-English Model-1",
          "is_primary": true,
          "description": "On newly tokenized IK(v-3) corpus 1.1 Million",
          "created_on": "2020-02-19T06:04:01.168Z",
          "status": "ACTIVE",
          "source_language_name":"Punjabi",
          "target_language_name":"English"
        },
        {
          "source_language_code": "en",
          "target_language_code": "bn",
          "model_id": 57,
          "model_name": "English-Bengali Model-2",
          "is_primary": false,
          "description": "On newly tokenized IK(v-3) corpus 1.1 Million",
          "created_on": "2020-02-20T05:00:28.797Z",
          "status": "ACTIVE",
          "source_language_name":"English",
          "target_language_name":"Bengali"
        },
        {
          "source_language_code": "bn",
          "target_language_code": "en",
          "model_id": 58,
          "model_name": "Bengali-English Model-1",
          "is_primary": true,
          "description": "On newly tokenized IK(v-3) corpus 1.1 Million",
          "created_on": "2020-02-20T05:01:01.725Z",
          "status": "ACTIVE",
          "source_language_name":"Bengali",
          "target_language_name":"English"
        },
        {
          "source_language_code": "en",
          "target_language_code": "ml",
          "model_id": 59,
          "model_name": "Eng-Malayalam Model-2",
          "is_primary": false,
          "description": "On newly tokenized IK corpus 1.1 Million",
          "created_on": "2020-02-24T05:45:25.651Z",
          "status": "ACTIVE",
          "source_language_name":"English",
          "target_language_name":"Malayalam"
        },
        {
          "source_language_code": "ml",
          "target_language_code": "en",
          "model_id": 60,
          "model_name": "Malayalam-English Model-1",
          "is_primary": true,
          "description": "On newly tokenized IK corpus 1.1 Million",
          "created_on": "2020-02-24T05:46:02.490Z",
          "status": "ACTIVE",
          "source_language_name":"Malayalam",
          "target_language_name":"English"
        },
        {
          "source_language_code": "mr",
          "target_language_code": "en",
          "model_id": 62,
          "model_name": "Marathi-English Model-2",
          "is_primary": true,
          "description": "On newly tokenized IK corpus 1 Million- cleaned over ik-V3",
          "created_on": "2020-03-01T11:52:56.912Z",
          "status": "ACTIVE",
          "source_language_name":"Marathi",
          "target_language_name":"English"
        },
        {
          "source_language_code": "ta",
          "target_language_code": "en",
          "model_id": 61,
          "model_name": "Tamil-English Model-3",
          "is_primary": false,
          "description": "On newly tokenized IK corpus 1 Million- cleaned over ik-V3",
          "created_on": "2020-03-01T11:53:54.068Z",
          "status": "ACTIVE",
          "source_language_name":"Tamil",
          "target_language_name":"English"
        },
        {
          "source_language_code": "en",
          "target_language_code": "hi",
          "model_id": 63,
          "model_name": "Eng-hin Exp-13",
          "is_primary": false,
          "description": "ik-V3, size 2M",
          "created_on": "2020-03-12T05:35:01.005Z",
          "status": "ACTIVE",
          "source_language_name":"English",
          "target_language_name":"Hindi"
        },
        {
          "source_language_code": "hi",
          "target_language_code": "en",
          "model_id": 6,
          "model_name": "Hi-En_Model_Exp-2",
          "is_primary": true,
          "description": "Replicating Exp-5.6",
          "created_on": "2020-05-07T06:30:53.952Z",
          "status": "ACTIVE",
          "source_language_name":"Hindi",
          "target_language_name":"English"
        }
      ]
}