{"code": 200, "message": "request completed", "rsp": {"inputs": [{"file": {"identifier": "b66ae5f7-7c32-4cb3-a03a-ebf6c839e8b0", "name": "class_3.pdf", "format": "PDF"}, "config": {"OCR": {"option": "HIGH_ACCURACY", "language": "en"}}}], "jobID": "BM-15913540488115873", "state": "INITIATED", "status": "STARTED", "stepOrder": 0, "workflowCode": "abc", "taskID": "aaabbbba", "tool": "GVOCR", "message": "OCR", "metadata": {"module": "WORKFLOW-MANAGER", "receivedAt": 15993163946431696, "sessionID": "4M1qOZj53tIZsCoLNzP0oP", "userID": "d4e0b570-b72a-44e5-9110-5fdd54370a9d"}, "outputs": [{"status": {"message": "google-vision ocr run successfully"}, "page_info": ["upload/class_3_9898e65d-69fe-48b6-adde-907d50b369be/images/class_30001-1.jpg"], "file": {"file": {"identifier": "b66ae5f7-7c32-4cb3-a03a-ebf6c839e8b0", "name": "class_3.pdf", "format": "PDF"}, "config": {"OCR": {"option": "HIGH_ACCURACY", "language": "en"}}}, "pages": [{"identifier": "d673ab55-1f20-4c3f-a926-88531b776baa", "resolution": 300, "regions": [{"identifier": "4856c3cc-02c7-41f8-800b-cb92cf2130ee", "boundingBox": {"vertices": [{"x": 1236, "y": 311}, {"x": 1303, "y": 313}, {"x": 1302, "y": 352}, {"x": 1235, "y": 350}]}, "class": "PARA"}, {"identifier": "fa4648f2-ff9d-4709-b048-b6231a7daa0a", "boundingBox": {"vertices": [{"x": 550, "y": 462}, {"x": 2347, "y": 462}, {"x": 2347, "y": 585}, {"x": 550, "y": 585}]}, "class": "PARA"}, {"identifier": "64709272-2fc1-422a-afdf-7f772dbc9930", "boundingBox": {"vertices": [{"x": 550, "y": 660}, {"x": 2379, "y": 664}, {"x": 2379, "y": 787}, {"x": 550, "y": 783}]}, "class": "PARA"}, {"identifier": "c7b5f31d-e99c-4caa-b45d-acf867624498", "boundingBox": {"vertices": [{"x": 1100, "y": 897}, {"x": 1453, "y": 898}, {"x": 1453, "y": 936}, {"x": 1100, "y": 935}]}, "class": "PARA"}, {"identifier": "ae4a4abd-f610-4840-8f3f-1dfbdc92f467", "boundingBox": {"vertices": [{"x": 550, "y": 963}, {"x": 2349, "y": 963}, {"x": 2349, "y": 1124}, {"x": 550, "y": 1124}]}, "class": "PARA"}, {"identifier": "2d1255aa-b709-4d85-850b-fcffb74532a8", "boundingBox": {"vertices": [{"x": 545, "y": 1196}, {"x": 604, "y": 1197}, {"x": 603, "y": 1316}, {"x": 544, "y": 1315}]}, "class": "PARA"}, {"identifier": "e24cc8c9-9d52-4e6d-a89c-064f317d4401", "boundingBox": {"vertices": [{"x": 794, "y": 1187}, {"x": 2401, "y": 1195}, {"x": 2400, "y": 1389}, {"x": 793, "y": 1381}]}, "class": "PARA"}, {"identifier": "88da293e-035a-42d6-a372-d4958794b9ad", "boundingBox": {"vertices": [{"x": 557, "y": 1474}, {"x": 604, "y": 1475}, {"x": 603, "y": 1520}, {"x": 556, "y": 1519}]}, "class": "PARA"}, {"identifier": "ee23c6b2-c9a4-41e9-b315-399210faf2ce", "boundingBox": {"vertices": [{"x": 796, "y": 1471}, {"x": 2379, "y": 1478}, {"x": 2378, "y": 1644}, {"x": 795, "y": 1637}]}, "class": "PARA"}, {"identifier": "e2e63eb7-0070-47e6-aee0-b5a545ea2c4e", "boundingBox": {"vertices": [{"x": 556, "y": 1736}, {"x": 796, "y": 1736}, {"x": 796, "y": 1773}, {"x": 556, "y": 1773}]}, "class": "PARA"}, {"identifier": "2ab1123c-25ec-4341-b6d0-014b69a3e28e", "boundingBox": {"vertices": [{"x": 1839, "y": 1675}, {"x": 2076, "y": 1659}, {"x": 2092, "y": 1879}, {"x": 1854, "y": 1895}]}, "class": "PARA"}, {"identifier": "8a817cb0-9f79-477e-ae65-966b1c631fb4", "boundingBox": {"vertices": [{"x": 549, "y": 1861}, {"x": 696, "y": 1862}, {"x": 696, "y": 1898}, {"x": 549, "y": 1897}]}, "class": "PARA"}, {"identifier": "64b51297-6d96-4b7c-9876-d45f79f4ce30", "boundingBox": {"vertices": [{"x": 1710, "y": 1850}, {"x": 2322, "y": 1854}, {"x": 2322, "y": 1918}, {"x": 1710, "y": 1914}]}, "class": "PARA"}, {"identifier": "94886cec-4e21-497f-9eda-b7e9d9232e5c", "boundingBox": {"vertices": [{"x": 1132, "y": 2038}, {"x": 1489, "y": 2039}, {"x": 1489, "y": 2079}, {"x": 1132, "y": 2078}]}, "class": "PARA"}, {"identifier": "e7f012f3-3489-4b76-9708-f61e20ac6b89", "boundingBox": {"vertices": [{"x": 556, "y": 2178}, {"x": 2169, "y": 2178}, {"x": 2169, "y": 2307}, {"x": 556, "y": 2307}]}, "class": "PARA"}, {"identifier": "849ebc42-bbee-4a92-8e21-21dcb0e0bef1", "boundingBox": {"vertices": [{"x": 1056, "y": 2409}, {"x": 1063, "y": 2409}, {"x": 1063, "y": 2422}, {"x": 1056, "y": 2422}]}, "class": "PARA"}, {"identifier": "b99d9256-f5dd-4b1c-83a4-615c27c1e24b", "boundingBox": {"vertices": [{"x": 1837, "y": 2302}, {"x": 2073, "y": 2299}, {"x": 2076, "y": 2523}, {"x": 1840, "y": 2526}]}, "class": "PARA"}, {"identifier": "058d2911-4d78-461c-9678-9603414b1dec", "boundingBox": {"vertices": [{"x": 433, "y": 2457}, {"x": 436, "y": 2457}, {"x": 436, "y": 2468}, {"x": 433, "y": 2468}]}, "class": "PARA"}, {"identifier": "a3aeeb03-2ecd-4827-804b-6d2943f2aba0", "boundingBox": {"vertices": [{"x": 1712, "y": 2523}, {"x": 2315, "y": 2523}, {"x": 2315, "y": 2589}, {"x": 1712, "y": 2589}]}, "class": "PARA"}, {"identifier": "7ad0bc58-c3d5-45cb-8df9-762338e468d3", "boundingBox": {"vertices": [{"x": 2157, "y": 2949}, {"x": 2160, "y": 2949}, {"x": 2160, "y": 2963}, {"x": 2157, "y": 2963}]}, "class": "PARA"}], "lines": [{"identifier": "c53c7cda-cbe2-4a9c-baa1-835ad9afd03c", "boundingBox": {"vertices": [{"x": 1236, "y": 311}, {"x": 1303, "y": 311}, {"x": 1302, "y": 352}, {"x": 1235, "y": 352}]}, "text": "- 2"}, {"identifier": "8b0282c6-2451-435d-bbc4-a96fb5b85d8d", "boundingBox": {"vertices": [{"x": 552, "y": 462}, {"x": 2347, "y": 462}, {"x": 2347, "y": 517}, {"x": 552, "y": 517}]}, "text": "trial court ought to have seen that the contradictions were "}, {"identifier": "63750087-0fe1-47fc-923f-32afeba3e644", "boundingBox": {"vertices": [{"x": 550, "y": 539}, {"x": 936, "y": 539}, {"x": 936, "y": 584}, {"x": 550, "y": 584}]}, "text": "not material."}, {"identifier": "77e685d4-55cf-468e-9a10-e79312bea227", "boundingBox": {"vertices": [{"x": 552, "y": 664}, {"x": 2379, "y": 664}, {"x": 2379, "y": 721}, {"x": 552, "y": 721}]}, "text": "5) :. That the Judgment is otherwise wrong and illegal and "}, {"identifier": "3b5fcfa5-2082-4238-aacb-7269dc89286b", "boundingBox": {"vertices": [{"x": 550, "y": 738}, {"x": 1303, "y": 738}, {"x": 1303, "y": 785}, {"x": 550, "y": 785}]}, "text": "deserves to be set aside."}, {"identifier": "f2933aed-f7b2-41cc-82bb-c0b1bb6a45e9", "boundingBox": {"vertices": [{"x": 1100, "y": 898}, {"x": 1453, "y": 898}, {"x": 1453, "y": 936}, {"x": 1100, "y": 936}]}, "text": "PRA Y ER."}, {"identifier": "386d5cdc-0da8-49c3-9928-e81f3ede13eb", "boundingBox": {"vertices": [{"x": 798, "y": 994}, {"x": 2349, "y": 994}, {"x": 2349, "y": 1049}, {"x": 798, "y": 1049}]}, "text": "It is, therefore, prayed that this Hon'ble court be"}, {"identifier": "f034a78d-d78f-4280-8285-8727e9bc97bc", "boundingBox": {"vertices": [{"x": 1293, "y": 963}, {"x": 1318, "y": 963}, {"x": 1318, "y": 1051}, {"x": 1293, "y": 1051}]}, "text": ", "}, {"identifier": "4bd91235-67e7-4c0e-9bc6-1d59f14229aa", "boundingBox": {"vertices": [{"x": 550, "y": 1069}, {"x": 879, "y": 1069}, {"x": 879, "y": 1124}, {"x": 550, "y": 1124}]}, "text": "pleased to:"}, {"identifier": "814d9f07-1d07-432a-8a2f-9b4cc622a995", "boundingBox": {"vertices": [{"x": 545, "y": 1197}, {"x": 603, "y": 1197}, {"x": 602, "y": 1243}, {"x": 544, "y": 1243}]}, "text": "1) "}, {"identifier": "52d37b25-a3cd-4a12-a00f-b49574d15ec0", "boundingBox": {"vertices": [{"x": 552, "y": 1266}, {"x": 603, "y": 1266}, {"x": 603, "y": 1315}, {"x": 552, "y": 1315}]}, "text": "2)"}, {"identifier": "fd36df36-772f-4242-9732-6e0a5cf27be9", "boundingBox": {"vertices": [{"x": 794, "y": 1188}, {"x": 2401, "y": 1188}, {"x": 2401, "y": 1253}, {"x": 794, "y": 1253}]}, "text": "Grant leave to appeal against the impugned Judgement. "}, {"identifier": "1f0f5995-a583-4b0a-8ff4-38d0d80b0807", "boundingBox": {"vertices": [{"x": 796, "y": 1272}, {"x": 2225, "y": 1272}, {"x": 2225, "y": 1329}, {"x": 796, "y": 1329}]}, "text": "Set aside the impugned Judgment and convict the "}, {"identifier": "624361ed-20d8-40d4-9358-aeaf21db3ddd", "boundingBox": {"vertices": [{"x": 795, "y": 1318}, {"x": 2129, "y": 1318}, {"x": 2129, "y": 1381}, {"x": 795, "y": 1381}]}, "text": "respondents/accused of the offences charged."}, {"identifier": "5c99ff0b-120f-4653-a4ab-59c6ebeeaa54", "boundingBox": {"vertices": [{"x": 557, "y": 1474}, {"x": 604, "y": 1475}, {"x": 603, "y": 1520}, {"x": 556, "y": 1520}]}, "text": "3)"}, {"identifier": "863f4e1e-e9ff-490e-9552-ccd785072be0", "boundingBox": {"vertices": [{"x": 796, "y": 1472}, {"x": 2349, "y": 1472}, {"x": 2349, "y": 1535}, {"x": 796, "y": 1535}]}, "text": "Proceed 390 Cr.P.C. against the respondents/accused "}, {"identifier": "0c41d295-afa5-426c-8c4a-47a93a262661", "boundingBox": {"vertices": [{"x": 796, "y": 1530}, {"x": 2378, "y": 1530}, {"x": 2378, "y": 1593}, {"x": 796, "y": 1593}]}, "text": "during the pendency of this application for leave to "}, {"identifier": "c7a74126-1fe1-43bc-8db5-b26b5abd1f68", "boundingBox": {"vertices": [{"x": 798, "y": 1578}, {"x": 1213, "y": 1578}, {"x": 1213, "y": 1637}, {"x": 798, "y": 1637}]}, "text": "appeal/appeal."}, {"identifier": "6bbd1988-a6e7-4e44-b481-c64a66071608", "boundingBox": {"vertices": [{"x": 556, "y": 1736}, {"x": 796, "y": 1736}, {"x": 796, "y": 1773}, {"x": 556, "y": 1773}]}, "text": "JABALPUR"}, {"identifier": "0549bac8-7f9d-4a96-b500-39d911a98f6e", "boundingBox": {"vertices": [{"x": 1839, "y": 1663}, {"x": 2077, "y": 1659}, {"x": 2092, "y": 1894}, {"x": 1854, "y": 1895}]}, "text": "borneo"}, {"identifier": "e74eb8ad-7baa-4bbf-a7d0-d9d4098d22e4", "boundingBox": {"vertices": [{"x": 549, "y": 1862}, {"x": 696, "y": 1862}, {"x": 696, "y": 1898}, {"x": 549, "y": 1898}]}, "text": "DATE:"}, {"identifier": "b5647487-b749-4d38-8906-e11534eb4431", "boundingBox": {"vertices": [{"x": 1710, "y": 1864}, {"x": 2315, "y": 1864}, {"x": 2315, "y": 1907}, {"x": 1710, "y": 1907}]}, "text": "GOVERNMENT ADVOCATE."}, {"identifier": "4946750a-06c8-4ad7-ac68-aa5c6835e4ba", "boundingBox": {"vertices": [{"x": 2304, "y": 1854}, {"x": 2322, "y": 1854}, {"x": 2322, "y": 1918}, {"x": 2304, "y": 1918}]}, "text": "."}, {"identifier": "06d36b39-5601-4fff-8ca9-fffac5daab1e", "boundingBox": {"vertices": [{"x": 1132, "y": 2039}, {"x": 1489, "y": 2039}, {"x": 1489, "y": 2079}, {"x": 1132, "y": 2079}]}, "text": "CERTIFICATE."}, {"identifier": "2d218748-2d54-4e62-97e4-9d279b12326c", "boundingBox": {"vertices": [{"x": 802, "y": 2178}, {"x": 2169, "y": 2178}, {"x": 2169, "y": 2239}, {"x": 802, "y": 2239}]}, "text": "Certified that I have been instructedst by the "}, {"identifier": "f2260d94-e67a-4fe0-86df-f93c6a084dda", "boundingBox": {"vertices": [{"x": 556, "y": 2262}, {"x": 1977, "y": 2262}, {"x": 1977, "y": 2307}, {"x": 556, "y": 2307}]}, "text": "State Government fo file and conduct this case."}, {"identifier": "a8465584-3aea-4628-91f3-a5304cf4a82d", "boundingBox": {"vertices": [{"x": 1056, "y": 2409}, {"x": 1063, "y": 2409}, {"x": 1063, "y": 2422}, {"x": 1056, "y": 2422}]}, "text": "2"}, {"identifier": "dbf23ed2-ecfe-416a-a1b3-807a5a0865c4", "boundingBox": {"vertices": [{"x": 1837, "y": 2300}, {"x": 2073, "y": 2299}, {"x": 2076, "y": 2525}, {"x": 1840, "y": 2526}]}, "text": "Emma"}, {"identifier": "05e835a6-61e1-4214-8c82-8667c14a6133", "boundingBox": {"vertices": [{"x": 433, "y": 2457}, {"x": 436, "y": 2457}, {"x": 436, "y": 2468}, {"x": 433, "y": 2468}]}, "text": "."}, {"identifier": "520e12d1-a92d-418b-b024-1c5a60754fa5", "boundingBox": {"vertices": [{"x": 1712, "y": 2523}, {"x": 2315, "y": 2523}, {"x": 2315, "y": 2589}, {"x": 1712, "y": 2589}]}, "text": "GOVERNMENT ADVOCATE."}, {"identifier": "a0b5baad-9f2c-4fa3-8233-11dd3ca9d0bd", "boundingBox": {"vertices": [{"x": 2157, "y": 2949}, {"x": 2160, "y": 2949}, {"x": 2160, "y": 2963}, {"x": 2157, "y": 2963}]}, "text": "1"}], "words": [{"identifier": "6f97d080-3e45-4f2c-9cd2-4f2c92ff213c", "boundingBox": {"vertices": [{"x": 1236, "y": 311}, {"x": 1247, "y": 311}, {"x": 1246, "y": 350}, {"x": 1235, "y": 350}]}, "text": "-", "confidence": 0.5099999904632568, "language": "en"}, {"identifier": "8dd70606-22d3-4235-930b-60dead5e8641", "boundingBox": {"vertices": [{"x": 1292, "y": 313}, {"x": 1303, "y": 313}, {"x": 1302, "y": 352}, {"x": 1291, "y": 352}]}, "text": "2", "confidence": 0.9300000071525574, "language": "en"}, {"identifier": "47578058-1dcf-430f-8472-4b26d242d82d", "boundingBox": {"vertices": [{"x": 552, "y": 462}, {"x": 697, "y": 462}, {"x": 697, "y": 517}, {"x": 552, "y": 517}]}, "text": "trial", "confidence": 0.9900000095367432, "language": "en"}, {"identifier": "56b71b3e-3292-4501-9171-8a2f82187f09", "boundingBox": {"vertices": [{"x": 740, "y": 462}, {"x": 880, "y": 462}, {"x": 880, "y": 517}, {"x": 740, "y": 517}]}, "text": "court", "confidence": 0.9900000095367432, "language": "en"}, {"identifier": "cde2f192-da01-44ab-b239-b1f818e17096", "boundingBox": {"vertices": [{"x": 918, "y": 462}, {"x": 1065, "y": 462}, {"x": 1065, "y": 517}, {"x": 918, "y": 517}]}, "text": "ought", "confidence": 0.9900000095367432, "language": "en"}, {"identifier": "2d6d2ad7-1b38-4edf-a3e1-5e383efae27e", "boundingBox": {"vertices": [{"x": 1102, "y": 462}, {"x": 1159, "y": 462}, {"x": 1159, "y": 517}, {"x": 1102, "y": 517}]}, "text": "to", "confidence": 1.0, "language": "en"}, {"identifier": "5bdbd333-1a21-411c-8280-27068b7f93ab", "boundingBox": {"vertices": [{"x": 1188, "y": 462}, {"x": 1309, "y": 462}, {"x": 1309, "y": 517}, {"x": 1188, "y": 517}]}, "text": "have", "confidence": 0.9900000095367432, "language": "en"}, {"identifier": "49ffeae4-2bbb-4790-a8d9-4b0f4cadb051", "boundingBox": {"vertices": [{"x": 1344, "y": 462}, {"x": 1463, "y": 462}, {"x": 1463, "y": 517}, {"x": 1344, "y": 517}]}, "text": "seen", "confidence": 0.9900000095367432, "language": "en"}, {"identifier": "4d6cdd00-a12d-4f86-9879-2b0768ccab68", "boundingBox": {"vertices": [{"x": 1500, "y": 462}, {"x": 1615, "y": 462}, {"x": 1615, "y": 517}, {"x": 1500, "y": 517}]}, "text": "that", "confidence": 0.9900000095367432, "language": "en"}, {"identifier": "811d8181-b559-4448-949f-e72c5703f95d", "boundingBox": {"vertices": [{"x": 1650, "y": 462}, {"x": 1737, "y": 462}, {"x": 1737, "y": 517}, {"x": 1650, "y": 517}]}, "text": "the", "confidence": 0.9900000095367432, "language": "en"}, {"identifier": "235aa7b9-359f-4be3-a7b8-e99cd75e6f91", "boundingBox": {"vertices": [{"x": 1774, "y": 462}, {"x": 2193, "y": 462}, {"x": 2193, "y": 517}, {"x": 1774, "y": 517}]}, "text": "contradictions", "confidence": 0.9900000095367432, "language": "en"}, {"identifier": "10fc7ebf-c24e-4083-b7c3-1eb0481a8599", "boundingBox": {"vertices": [{"x": 2226, "y": 462}, {"x": 2347, "y": 462}, {"x": 2347, "y": 517}, {"x": 2226, "y": 517}]}, "text": "were", "confidence": 0.9900000095367432, "language": "en"}, {"identifier": "495c6c39-00db-4c1a-970d-c590f072baae", "boundingBox": {"vertices": [{"x": 550, "y": 542}, {"x": 636, "y": 541}, {"x": 636, "y": 584}, {"x": 550, "y": 585}]}, "text": "not", "confidence": 0.9900000095367432, "language": "en"}, {"identifier": "8f4a93c2-f6a4-42c5-9fef-ec724bcb4607", "boundingBox": {"vertices": [{"x": 667, "y": 541}, {"x": 908, "y": 539}, {"x": 908, "y": 582}, {"x": 667, "y": 584}]}, "text": "material", "confidence": 0.9900000095367432, "language": "en"}, {"identifier": "5ab40159-1648-4753-b5b5-fee155224a00", "boundingBox": {"vertices": [{"x": 921, "y": 539}, {"x": 936, "y": 539}, {"x": 936, "y": 581}, {"x": 921, "y": 581}]}, "text": ".", "confidence": 0.9900000095367432, "language": "en"}, {"identifier": "30732492-4dde-40df-825b-301dce1b752e", "boundingBox": {"vertices": [{"x": 552, "y": 664}, {"x": 574, "y": 664}, {"x": 574, "y": 710}, {"x": 552, "y": 710}]}, "text": "5", "confidence": 0.9900000095367432, "language": "en"}, {"identifier": "06dba57b-b3ee-4e6b-b855-e755db7b93b6", "boundingBox": {"vertices": [{"x": 588, "y": 664}, {"x": 600, "y": 664}, {"x": 600, "y": 710}, {"x": 588, "y": 710}]}, "text": ")", "confidence": 0.9700000286102295, "language": "en"}, {"identifier": "63e5ad42-411f-47b4-a429-24fd6e5ec881", "boundingBox": {"vertices": [{"x": 744, "y": 664}, {"x": 747, "y": 664}, {"x": 747, "y": 721}, {"x": 744, "y": 721}]}, "text": ":", "confidence": 0.3400000035762787, "language": "en"}, {"identifier": "1e4c4d34-9789-4dc7-9dfd-2745d3cab461", "boundingBox": {"vertices": [{"x": 768, "y": 664}, {"x": 771, "y": 664}, {"x": 771, "y": 721}, {"x": 768, "y": 721}]}, "text": ".", "confidence": 0.49000000953674316, "language": "en"}, {"identifier": "e89a7d81-4bdb-4c43-81f2-ccbea8a182c0", "boundingBox": {"vertices": [{"x": 796, "y": 664}, {"x": 913, "y": 664}, {"x": 913, "y": 721}, {"x": 796, "y": 721}]}, "text": "That", "confidence": 0.8700000047683716, "language": "en"}, {"identifier": "ca0452e1-f736-40d7-8675-79fe76c5930c", "boundingBox": {"vertices": [{"x": 950, "y": 664}, {"x": 1033, "y": 664}, {"x": 1033, "y": 721}, {"x": 950, "y": 721}]}, "text": "the", "confidence": 0.9200000166893005, "language": "en"}, {"identifier": "b7ff10f2-e493-47a9-8a95-f5b527d742dd", "boundingBox": {"vertices": [{"x": 1068, "y": 664}, {"x": 1313, "y": 664}, {"x": 1313, "y": 721}, {"x": 1068, "y": 721}]}, "text": "Judgment", "confidence": 0.9800000190734863, "language": "en"}, {"identifier": "00f86d20-b32d-4513-a83c-a329557fff26", "boundingBox": {"vertices": [{"x": 1346, "y": 664}, {"x": 1397, "y": 664}, {"x": 1397, "y": 721}, {"x": 1346, "y": 721}]}, "text": "is", "confidence": 0.9900000095367432, "language": "en"}, {"identifier": "5e62d5bf-70fc-4d62-8749-1d5372ff0b24", "boundingBox": {"vertices": [{"x": 1436, "y": 664}, {"x": 1705, "y": 664}, {"x": 1705, "y": 721}, {"x": 1436, "y": 721}]}, "text": "otherwise", "confidence": 0.9900000095367432, "language": "en"}, {"identifier": "6678e205-148c-49c7-a295-17332df3bfe1", "boundingBox": {"vertices": [{"x": 1736, "y": 664}, {"x": 1889, "y": 664}, {"x": 1889, "y": 721}, {"x": 1736, "y": 721}]}, "text": "wrong", "confidence": 0.9900000095367432, "language": "en"}, {"identifier": "3b7e72e0-d31d-45de-9f6a-07e75e131a46", "boundingBox": {"vertices": [{"x": 1928, "y": 664}, {"x": 2010, "y": 664}, {"x": 2010, "y": 721}, {"x": 1928, "y": 721}]}, "text": "and", "confidence": 0.9900000095367432, "language": "en"}, {"identifier": "0b142234-0932-4920-8457-bff62e62e704", "boundingBox": {"vertices": [{"x": 2056, "y": 664}, {"x": 2262, "y": 664}, {"x": 2262, "y": 721}, {"x": 2056, "y": 721}]}, "text": "illegal", "confidence": 0.9599999785423279, "language": "en"}, {"identifier": "31b0dc38-f567-4b8b-9b22-5a0c0f58023f", "boundingBox": {"vertices": [{"x": 2292, "y": 664}, {"x": 2379, "y": 664}, {"x": 2379, "y": 721}, {"x": 2292, "y": 721}]}, "text": "and", "confidence": 0.9900000095367432, "language": "en"}, {"identifier": "dedf1ef4-ebbc-48e2-9b71-be9d1801e168", "boundingBox": {"vertices": [{"x": 550, "y": 737}, {"x": 793, "y": 738}, {"x": 793, "y": 782}, {"x": 550, "y": 781}]}, "text": "deserves", "confidence": 0.9900000095367432, "language": "en"}, {"identifier": "7ad346e4-c4e3-4b14-b942-29d0f6f18064", "boundingBox": {"vertices": [{"x": 828, "y": 739}, {"x": 883, "y": 739}, {"x": 883, "y": 782}, {"x": 828, "y": 782}]}, "text": "to", "confidence": 0.9900000095367432, "language": "en"}, {"identifier": "70790d94-794a-4d45-a1b6-a48b1d9912fb", "boundingBox": {"vertices": [{"x": 914, "y": 740}, {"x": 975, "y": 740}, {"x": 975, "y": 783}, {"x": 914, "y": 783}]}, "text": "be", "confidence": 0.9900000095367432, "language": "en"}, {"identifier": "38774d6b-15e2-4ea4-a54a-2dacf9185836", "boundingBox": {"vertices": [{"x": 1010, "y": 740}, {"x": 1097, "y": 740}, {"x": 1097, "y": 783}, {"x": 1010, "y": 783}]}, "text": "set", "confidence": 0.9900000095367432, "language": "en"}, {"identifier": "51c9c072-4fa0-4668-892b-70e4b52b0629", "boundingBox": {"vertices": [{"x": 1132, "y": 740}, {"x": 1279, "y": 741}, {"x": 1279, "y": 785}, {"x": 1132, "y": 784}]}, "text": "aside", "confidence": 0.9900000095367432, "language": "en"}, {"identifier": "83e97263-c04e-4f41-9c07-56c1707d3555", "boundingBox": {"vertices": [{"x": 1294, "y": 742}, {"x": 1303, "y": 742}, {"x": 1303, "y": 785}, {"x": 1294, "y": 785}]}, "text": ".", "confidence": 0.9800000190734863, "language": "en"}, {"identifier": "eb36572c-4b76-4f87-b2a3-661f0b037f43", "boundingBox": {"vertices": [{"x": 1100, "y": 898}, {"x": 1246, "y": 899}, {"x": 1246, "y": 936}, {"x": 1100, "y": 935}]}, "text": "PRA", "confidence": 0.800000011920929, "language": "no"}, {"identifier": "b777b542-eced-46ba-ac00-fc510802397d", "boundingBox": {"vertices": [{"x": 1292, "y": 898}, {"x": 1302, "y": 898}, {"x": 1302, "y": 935}, {"x": 1292, "y": 935}]}, "text": "Y", "confidence": 0.8500000238418579, "language": "no"}, {"identifier": "5ac4eda8-5b20-4547-8eee-d6e5d03bd444", "boundingBox": {"vertices": [{"x": 1328, "y": 898}, {"x": 1442, "y": 898}, {"x": 1442, "y": 936}, {"x": 1328, "y": 936}]}, "text": "ER", "confidence": 0.7300000190734863, "language": "no"}, {"identifier": "b2777fff-025f-429f-9ded-380394631768", "boundingBox": {"vertices": [{"x": 1443, "y": 899}, {"x": 1453, "y": 899}, {"x": 1453, "y": 936}, {"x": 1443, "y": 936}]}, "text": ".", "confidence": 0.6499999761581421, "language": "no"}, {"identifier": "ee57f7b7-f7ea-4384-8c3b-1a14c10fdafe", "boundingBox": {"vertices": [{"x": 798, "y": 994}, {"x": 853, "y": 994}, {"x": 853, "y": 1049}, {"x": 798, "y": 1049}]}, "text": "It", "confidence": 0.9900000095367432, "language": "en"}, {"identifier": "c610e15a-d830-4bc7-8fe9-bf2c53a0154d", "boundingBox": {"vertices": [{"x": 888, "y": 994}, {"x": 941, "y": 994}, {"x": 941, "y": 1049}, {"x": 888, "y": 1049}]}, "text": "is", "confidence": 0.9900000095367432, "language": "en"}, {"identifier": "8cb3c4ea-a725-460f-84e8-cabf137e2568", "boundingBox": {"vertices": [{"x": 954, "y": 994}, {"x": 967, "y": 994}, {"x": 967, "y": 1049}, {"x": 954, "y": 1049}]}, "text": ",", "confidence": 0.9900000095367432, "language": "en"}, {"identifier": "5103bbdf-0408-4d71-862b-5a2cd799ca6c", "boundingBox": {"vertices": [{"x": 1010, "y": 994}, {"x": 1281, "y": 994}, {"x": 1281, "y": 1049}, {"x": 1010, "y": 1049}]}, "text": "therefore", "confidence": 0.9900000095367432, "language": "en"}, {"identifier": "29a67159-0447-4521-881e-bd8a1577bb0e", "boundingBox": {"vertices": [{"x": 1290, "y": 994}, {"x": 1301, "y": 994}, {"x": 1301, "y": 1049}, {"x": 1290, "y": 1049}]}, "text": ",", "confidence": 1.0, "language": "en"}, {"identifier": "a35b73d5-8015-4a87-841d-9d0ca13f5856", "boundingBox": {"vertices": [{"x": 1342, "y": 994}, {"x": 1523, "y": 994}, {"x": 1523, "y": 1049}, {"x": 1342, "y": 1049}]}, "text": "prayed", "confidence": 0.9900000095367432, "language": "en"}, {"identifier": "35007b58-2780-4a09-b078-f10913ab54a7", "boundingBox": {"vertices": [{"x": 1560, "y": 994}, {"x": 1677, "y": 994}, {"x": 1677, "y": 1049}, {"x": 1560, "y": 1049}]}, "text": "that", "confidence": 0.9900000095367432, "language": "en"}, {"identifier": "b72657e1-b272-40d9-9dc2-2f8ac023bf58", "boundingBox": {"vertices": [{"x": 1712, "y": 994}, {"x": 1825, "y": 994}, {"x": 1825, "y": 1049}, {"x": 1712, "y": 1049}]}, "text": "this", "confidence": 0.9900000095367432, "language": "en"}, {"identifier": "9a6cb7c8-d6c1-4688-bac8-6439ba41e0e2", "boundingBox": {"vertices": [{"x": 1864, "y": 994}, {"x": 2073, "y": 994}, {"x": 2073, "y": 1049}, {"x": 1864, "y": 1049}]}, "text": "Hon'ble", "confidence": 0.9900000095367432, "language": "en"}, {"identifier": "2a7da4f1-1681-4168-88fb-401d1ad80056", "boundingBox": {"vertices": [{"x": 2112, "y": 994}, {"x": 2257, "y": 994}, {"x": 2257, "y": 1049}, {"x": 2112, "y": 1049}]}, "text": "court", "confidence": 0.9800000190734863, "language": "en"}, {"identifier": "0f46c8f0-c40e-477b-8da5-f9ad856da478", "boundingBox": {"vertices": [{"x": 2288, "y": 994}, {"x": 2349, "y": 994}, {"x": 2349, "y": 1049}, {"x": 2288, "y": 1049}]}, "text": "be", "confidence": 0.9700000286102295, "language": "en"}, {"identifier": "18445b20-7425-4bd6-a09d-4ec80d3445f5", "boundingBox": {"vertices": [{"x": 1293, "y": 963}, {"x": 1318, "y": 963}, {"x": 1318, "y": 1051}, {"x": 1293, "y": 1051}]}, "text": ",", "confidence": 1.0, "language": "en"}, {"identifier": "cc2459aa-6086-4bdc-8028-0e64d0941202", "boundingBox": {"vertices": [{"x": 550, "y": 1069}, {"x": 760, "y": 1069}, {"x": 760, "y": 1124}, {"x": 550, "y": 1124}]}, "text": "pleased", "confidence": 0.9900000095367432, "language": "en"}, {"identifier": "73aec91d-a94a-4d67-b2f2-19517effbbcb", "boundingBox": {"vertices": [{"x": 797, "y": 1069}, {"x": 854, "y": 1069}, {"x": 854, "y": 1124}, {"x": 797, "y": 1124}]}, "text": "to", "confidence": 0.9900000095367432, "language": "en"}, {"identifier": "c40bc5db-febb-4290-88f0-8c54cdcf1068", "boundingBox": {"vertices": [{"x": 865, "y": 1069}, {"x": 879, "y": 1069}, {"x": 879, "y": 1124}, {"x": 865, "y": 1124}]}, "text": ":", "confidence": 0.9599999785423279, "language": "en"}, {"identifier": "bbf1bd8f-ae4e-4283-bac2-59b5e0c1970b", "boundingBox": {"vertices": [{"x": 545, "y": 1197}, {"x": 571, "y": 1197}, {"x": 570, "y": 1243}, {"x": 544, "y": 1243}]}, "text": "1", "confidence": 0.8500000238418579, "language": "en"}, {"identifier": "2fd509b7-8490-4518-bc13-3482b2338768", "boundingBox": {"vertices": [{"x": 591, "y": 1197}, {"x": 603, "y": 1197}, {"x": 602, "y": 1243}, {"x": 590, "y": 1243}]}, "text": ")", "confidence": 0.9300000071525574, "language": "en"}, {"identifier": "df655e4e-5d36-4d2b-84dd-5ab208e5e0e7", "boundingBox": {"vertices": [{"x": 552, "y": 1266}, {"x": 577, "y": 1266}, {"x": 577, "y": 1315}, {"x": 552, "y": 1315}]}, "text": "2", "confidence": 0.9900000095367432, "language": "en"}, {"identifier": "b9e169d1-cb55-4ea8-8ac0-8734ec3eb186", "boundingBox": {"vertices": [{"x": 590, "y": 1266}, {"x": 603, "y": 1266}, {"x": 603, "y": 1315}, {"x": 590, "y": 1315}]}, "text": ")", "confidence": 0.9900000095367432, "language": "en"}, {"identifier": "1140babb-67b9-4751-87c0-877ecf1725c9", "boundingBox": {"vertices": [{"x": 794, "y": 1187}, {"x": 945, "y": 1188}, {"x": 945, "y": 1246}, {"x": 794, "y": 1245}]}, "text": "Grant", "confidence": 0.9800000190734863, "language": "en"}, {"identifier": "7a4305f8-828c-4861-ae2d-cf99976b9e0e", "boundingBox": {"vertices": [{"x": 966, "y": 1188}, {"x": 1129, "y": 1189}, {"x": 1129, "y": 1247}, {"x": 966, "y": 1246}]}, "text": "leave", "confidence": 0.9800000190734863, "language": "en"}, {"identifier": "a37cac3d-626c-4dcf-9bbd-6835bb89a731", "boundingBox": {"vertices": [{"x": 1164, "y": 1189}, {"x": 1221, "y": 1189}, {"x": 1221, "y": 1247}, {"x": 1164, "y": 1247}]}, "text": "to", "confidence": 0.9900000095367432, "language": "en"}, {"identifier": "78e3652c-bf17-4c24-b676-bfa4f189f112", "boundingBox": {"vertices": [{"x": 1252, "y": 1189}, {"x": 1429, "y": 1190}, {"x": 1429, "y": 1248}, {"x": 1252, "y": 1247}]}, "text": "appeal", "confidence": 0.9900000095367432, "language": "en"}, {"identifier": "f75e5c0c-1f2c-434e-9ca7-233fb0dc640a", "boundingBox": {"vertices": [{"x": 1468, "y": 1191}, {"x": 1677, "y": 1192}, {"x": 1677, "y": 1249}, {"x": 1468, "y": 1248}]}, "text": "against", "confidence": 0.9900000095367432, "language": "en"}, {"identifier": "40432ff5-40ad-4f3b-a1a3-32f919d695ef", "boundingBox": {"vertices": [{"x": 1712, "y": 1192}, {"x": 1799, "y": 1192}, {"x": 1799, "y": 1249}, {"x": 1712, "y": 1249}]}, "text": "the", "confidence": 1.0, "language": "en"}, {"identifier": "279f1ad2-831f-4475-a6f6-c494df7f8d27", "boundingBox": {"vertices": [{"x": 1834, "y": 1192}, {"x": 2073, "y": 1193}, {"x": 2073, "y": 1251}, {"x": 1834, "y": 1250}]}, "text": "impugned", "confidence": 0.9599999785423279, "language": "en"}, {"identifier": "ff35b34a-44c7-4c0f-be5f-e4a44b83f088", "boundingBox": {"vertices": [{"x": 2106, "y": 1194}, {"x": 2376, "y": 1195}, {"x": 2376, "y": 1253}, {"x": 2106, "y": 1252}]}, "text": "Judgement", "confidence": 0.9700000286102295, "language": "en"}, {"identifier": "e295e9a7-d633-4e67-bb5d-fa3f71133cd4", "boundingBox": {"vertices": [{"x": 2389, "y": 1196}, {"x": 2401, "y": 1196}, {"x": 2401, "y": 1253}, {"x": 2389, "y": 1253}]}, "text": ".", "confidence": 0.8999999761581421, "language": "en"}, {"identifier": "8b714f64-a31e-4e84-a1a0-75adefca2047", "boundingBox": {"vertices": [{"x": 796, "y": 1272}, {"x": 885, "y": 1272}, {"x": 885, "y": 1329}, {"x": 796, "y": 1329}]}, "text": "Set", "confidence": 0.8899999856948853, "language": "en"}, {"identifier": "76c45076-6b31-44e7-a1b7-5957e96fbc45", "boundingBox": {"vertices": [{"x": 918, "y": 1272}, {"x": 1067, "y": 1272}, {"x": 1067, "y": 1329}, {"x": 918, "y": 1329}]}, "text": "aside", "confidence": 0.9700000286102295, "language": "en"}, {"identifier": "2f692f37-db1a-4651-9b61-d04ed8697c7a", "boundingBox": {"vertices": [{"x": 1104, "y": 1272}, {"x": 1189, "y": 1272}, {"x": 1189, "y": 1329}, {"x": 1104, "y": 1329}]}, "text": "the", "confidence": 1.0, "language": "en"}, {"identifier": "c0b81f44-cc00-4cc6-927a-00f7dfbc1cd2", "boundingBox": {"vertices": [{"x": 1224, "y": 1272}, {"x": 1461, "y": 1272}, {"x": 1461, "y": 1329}, {"x": 1224, "y": 1329}]}, "text": "impugned", "confidence": 0.9900000095367432, "language": "en"}, {"identifier": "f9ff1b31-0822-4880-92f8-5ebb6ad0bc7b", "boundingBox": {"vertices": [{"x": 1496, "y": 1272}, {"x": 1739, "y": 1272}, {"x": 1739, "y": 1329}, {"x": 1496, "y": 1329}]}, "text": "Judgment", "confidence": 0.9900000095367432, "language": "en"}, {"identifier": "901e6110-0ef5-400d-8610-64719b73d4c5", "boundingBox": {"vertices": [{"x": 1774, "y": 1272}, {"x": 1859, "y": 1272}, {"x": 1859, "y": 1329}, {"x": 1774, "y": 1329}]}, "text": "and", "confidence": 0.9900000095367432, "language": "en"}, {"identifier": "a32f6868-f414-421d-8825-412453c60941", "boundingBox": {"vertices": [{"x": 1898, "y": 1272}, {"x": 2105, "y": 1272}, {"x": 2105, "y": 1329}, {"x": 1898, "y": 1329}]}, "text": "convict", "confidence": 0.9900000095367432, "language": "en"}, {"identifier": "864664bc-8436-4d7f-ab6d-d6c04921a28e", "boundingBox": {"vertices": [{"x": 2142, "y": 1272}, {"x": 2225, "y": 1272}, {"x": 2225, "y": 1329}, {"x": 2142, "y": 1329}]}, "text": "the", "confidence": 0.9900000095367432, "language": "en"}, {"identifier": "5c1e5bfa-5d7e-4002-8859-8bc144ded176", "boundingBox": {"vertices": [{"x": 795, "y": 1318}, {"x": 1129, "y": 1318}, {"x": 1129, "y": 1381}, {"x": 795, "y": 1381}]}, "text": "respondents", "confidence": 0.9900000095367432, "language": "en"}, {"identifier": "b65322cd-9147-4a3e-8563-93c39d50c28f", "boundingBox": {"vertices": [{"x": 1142, "y": 1318}, {"x": 1160, "y": 1318}, {"x": 1160, "y": 1381}, {"x": 1142, "y": 1381}]}, "text": "/", "confidence": 0.9900000095367432, "language": "en"}, {"identifier": "1569b2c5-2cb0-41f9-890c-1fd75a6d86fa", "boundingBox": {"vertices": [{"x": 1161, "y": 1318}, {"x": 1371, "y": 1318}, {"x": 1371, "y": 1381}, {"x": 1161, "y": 1381}]}, "text": "accused", "confidence": 0.9800000190734863, "language": "en"}, {"identifier": "c850db5d-ff15-4245-97c3-1d5d07014cbe", "boundingBox": {"vertices": [{"x": 1407, "y": 1318}, {"x": 1461, "y": 1318}, {"x": 1461, "y": 1381}, {"x": 1407, "y": 1381}]}, "text": "of", "confidence": 0.8500000238418579, "language": "en"}, {"identifier": "663e84cc-716a-414d-bfc5-c41b6b508937", "boundingBox": {"vertices": [{"x": 1506, "y": 1318}, {"x": 1596, "y": 1318}, {"x": 1596, "y": 1381}, {"x": 1506, "y": 1381}]}, "text": "the", "confidence": 1.0, "language": "en"}, {"identifier": "4cf8e9d0-bc52-491e-831d-3afc5b756986", "boundingBox": {"vertices": [{"x": 1625, "y": 1318}, {"x": 1859, "y": 1318}, {"x": 1859, "y": 1381}, {"x": 1625, "y": 1381}]}, "text": "offences", "confidence": 0.9900000095367432, "language": "en"}, {"identifier": "89d9a19f-2caa-4c94-a110-59cc5840457d", "boundingBox": {"vertices": [{"x": 1898, "y": 1318}, {"x": 2100, "y": 1318}, {"x": 2100, "y": 1381}, {"x": 1898, "y": 1381}]}, "text": "charged", "confidence": 0.9900000095367432, "language": "en"}, {"identifier": "1fa74a03-2a22-4608-937b-827b847e9769", "boundingBox": {"vertices": [{"x": 2118, "y": 1318}, {"x": 2129, "y": 1318}, {"x": 2129, "y": 1381}, {"x": 2118, "y": 1381}]}, "text": ".", "confidence": 0.9800000190734863, "language": "en"}, {"identifier": "0fe254c6-fa3f-4c97-8a79-f48c32bb42b3", "boundingBox": {"vertices": [{"x": 557, "y": 1474}, {"x": 579, "y": 1475}, {"x": 578, "y": 1520}, {"x": 556, "y": 1519}]}, "text": "3", "confidence": 0.949999988079071, "language": "en"}, {"identifier": "2c59a201-5e3e-4b5d-92e8-065dcf896a9c", "boundingBox": {"vertices": [{"x": 590, "y": 1475}, {"x": 604, "y": 1475}, {"x": 603, "y": 1520}, {"x": 589, "y": 1520}]}, "text": ")", "confidence": 0.9599999785423279, "language": "en"}, {"identifier": "b0ebd3b8-56ac-4212-ace9-2fca41876347", "boundingBox": {"vertices": [{"x": 796, "y": 1471}, {"x": 1005, "y": 1472}, {"x": 1005, "y": 1530}, {"x": 796, "y": 1529}]}, "text": "Proceed", "confidence": 0.9800000190734863, "language": "en"}, {"identifier": "f7dc9910-f919-4d5b-9976-6d88967c3eb8", "boundingBox": {"vertices": [{"x": 1044, "y": 1473}, {"x": 1127, "y": 1473}, {"x": 1127, "y": 1530}, {"x": 1044, "y": 1530}]}, "text": "390", "confidence": 0.9800000190734863, "language": "en"}, {"identifier": "48f2b3c2-0637-49b5-b3ea-70a6b29b6373", "boundingBox": {"vertices": [{"x": 1162, "y": 1473}, {"x": 1367, "y": 1474}, {"x": 1367, "y": 1531}, {"x": 1162, "y": 1530}]}, "text": "Cr.P.C.", "confidence": 0.7099999785423279, "language": "en"}, {"identifier": "c4d500ab-0e9a-4726-98a4-94c7e09a26b0", "boundingBox": {"vertices": [{"x": 1406, "y": 1474}, {"x": 1617, "y": 1475}, {"x": 1617, "y": 1533}, {"x": 1406, "y": 1532}]}, "text": "against", "confidence": 0.9700000286102295, "language": "en"}, {"identifier": "9bbf39a9-bb65-4401-b7f1-e4984ffe825d", "boundingBox": {"vertices": [{"x": 1652, "y": 1475}, {"x": 1739, "y": 1475}, {"x": 1739, "y": 1532}, {"x": 1652, "y": 1532}]}, "text": "the", "confidence": 1.0, "language": "en"}, {"identifier": "56386a52-426f-40a7-afc4-e5d5e5779821", "boundingBox": {"vertices": [{"x": 1772, "y": 1475}, {"x": 2102, "y": 1476}, {"x": 2102, "y": 1534}, {"x": 1772, "y": 1533}]}, "text": "respondents", "confidence": 0.9900000095367432, "language": "en"}, {"identifier": "6be5e519-d64e-42c5-b8a6-73e032d6377e", "boundingBox": {"vertices": [{"x": 2123, "y": 1477}, {"x": 2138, "y": 1477}, {"x": 2138, "y": 1534}, {"x": 2123, "y": 1534}]}, "text": "/", "confidence": 0.9800000190734863, "language": "en"}, {"identifier": "77ebb3ec-d430-4649-97c2-27301b8c7fa2", "boundingBox": {"vertices": [{"x": 2140, "y": 1477}, {"x": 2349, "y": 1478}, {"x": 2349, "y": 1536}, {"x": 2140, "y": 1535}]}, "text": "accused", "confidence": 0.9900000095367432, "language": "en"}, {"identifier": "f5f8933f-ad67-4e72-bb3e-dfc26a2c5a62", "boundingBox": {"vertices": [{"x": 796, "y": 1530}, {"x": 975, "y": 1530}, {"x": 975, "y": 1593}, {"x": 796, "y": 1593}]}, "text": "during", "confidence": 0.9900000095367432, "language": "en"}, {"identifier": "7f12820b-5143-4a65-aeeb-c14585f7919d", "boundingBox": {"vertices": [{"x": 996, "y": 1530}, {"x": 1097, "y": 1530}, {"x": 1097, "y": 1593}, {"x": 996, "y": 1593}]}, "text": "the", "confidence": 1.0, "language": "en"}, {"identifier": "d8c53b47-471b-41f5-a836-b4797ce794aa", "boundingBox": {"vertices": [{"x": 1131, "y": 1530}, {"x": 1375, "y": 1530}, {"x": 1375, "y": 1593}, {"x": 1131, "y": 1593}]}, "text": "pendency", "confidence": 0.9900000095367432, "language": "en"}, {"identifier": "b26f3eb7-075c-4b3a-8ff5-cf66f5d32f52", "boundingBox": {"vertices": [{"x": 1406, "y": 1530}, {"x": 1463, "y": 1530}, {"x": 1463, "y": 1593}, {"x": 1406, "y": 1593}]}, "text": "of", "confidence": 0.9900000095367432, "language": "en"}, {"identifier": "d7f7d6fa-8c5a-441d-be2b-20fa4055e931", "boundingBox": {"vertices": [{"x": 1500, "y": 1530}, {"x": 1615, "y": 1530}, {"x": 1615, "y": 1593}, {"x": 1500, "y": 1593}]}, "text": "this", "confidence": 0.9900000095367432, "language": "en"}, {"identifier": "2b0a4847-70a3-42ce-a603-a6bb69160a13", "boundingBox": {"vertices": [{"x": 1650, "y": 1530}, {"x": 1983, "y": 1530}, {"x": 1983, "y": 1593}, {"x": 1650, "y": 1593}]}, "text": "application", "confidence": 0.9900000095367432, "language": "en"}, {"identifier": "6a6cd30c-8dbf-46b6-8b92-1cf049b8b184", "boundingBox": {"vertices": [{"x": 2012, "y": 1530}, {"x": 2115, "y": 1530}, {"x": 2115, "y": 1593}, {"x": 2012, "y": 1593}]}, "text": "for", "confidence": 0.9800000190734863, "language": "en"}, {"identifier": "0959fb3a-fcc2-46f9-8afb-7a5ee080c3e8", "boundingBox": {"vertices": [{"x": 2138, "y": 1530}, {"x": 2289, "y": 1530}, {"x": 2289, "y": 1593}, {"x": 2138, "y": 1593}]}, "text": "leave", "confidence": 0.9900000095367432, "language": "en"}, {"identifier": "925309c0-7066-40b2-afde-fa8b184b2c66", "boundingBox": {"vertices": [{"x": 2333, "y": 1530}, {"x": 2378, "y": 1530}, {"x": 2378, "y": 1593}, {"x": 2333, "y": 1593}]}, "text": "to", "confidence": 0.9900000095367432, "language": "en"}, {"identifier": "e0c89163-0826-4675-8bc0-e18cadad0d4b", "boundingBox": {"vertices": [{"x": 798, "y": 1578}, {"x": 975, "y": 1578}, {"x": 975, "y": 1637}, {"x": 798, "y": 1637}]}, "text": "appeal", "confidence": 0.9900000095367432, "language": "en"}, {"identifier": "af5dba93-e2b7-4309-b55a-e3f0ae8ff399", "boundingBox": {"vertices": [{"x": 989, "y": 1578}, {"x": 1004, "y": 1578}, {"x": 1004, "y": 1637}, {"x": 989, "y": 1637}]}, "text": "/", "confidence": 0.9900000095367432, "language": "en"}, {"identifier": "09d16849-94a6-47c3-9a61-fe9fcfa47627", "boundingBox": {"vertices": [{"x": 1017, "y": 1578}, {"x": 1185, "y": 1578}, {"x": 1185, "y": 1637}, {"x": 1017, "y": 1637}]}, "text": "appeal", "confidence": 0.9900000095367432, "language": "en"}, {"identifier": "81b70f80-a800-4996-9761-73f8d14bdacc", "boundingBox": {"vertices": [{"x": 1198, "y": 1578}, {"x": 1213, "y": 1578}, {"x": 1213, "y": 1637}, {"x": 1198, "y": 1637}]}, "text": ".", "confidence": 0.9900000095367432, "language": "en"}, {"identifier": "7853d10e-fd38-427e-b517-1ca48dffb105", "boundingBox": {"vertices": [{"x": 556, "y": 1736}, {"x": 796, "y": 1736}, {"x": 796, "y": 1773}, {"x": 556, "y": 1773}]}, "text": "JABALPUR", "confidence": 0.9800000190734863, "language": "en"}, {"identifier": "01a533f2-3337-4b4f-8bc4-7ecf8a3cd529", "boundingBox": {"vertices": [{"x": 1839, "y": 1675}, {"x": 2076, "y": 1659}, {"x": 2092, "y": 1879}, {"x": 1854, "y": 1895}]}, "text": "borneo", "confidence": 0.5899999737739563, "language": "en"}, {"identifier": "9df2141e-8827-4c07-8e61-b121be7d95c7", "boundingBox": {"vertices": [{"x": 549, "y": 1861}, {"x": 662, "y": 1862}, {"x": 662, "y": 1898}, {"x": 549, "y": 1897}]}, "text": "DATE", "confidence": 0.9900000095367432, "language": "en"}, {"identifier": "62ed08f4-7b97-4482-a566-974cd5ee9e22", "boundingBox": {"vertices": [{"x": 687, "y": 1863}, {"x": 696, "y": 1863}, {"x": 696, "y": 1898}, {"x": 687, "y": 1898}]}, "text": ":", "confidence": 0.9100000262260437, "language": "en"}, {"identifier": "02681028-f2cb-4811-8e50-9baf05deab36", "boundingBox": {"vertices": [{"x": 1710, "y": 1863}, {"x": 2013, "y": 1865}, {"x": 2013, "y": 1905}, {"x": 1710, "y": 1903}]}, "text": "GOVERNMENT", "confidence": 0.9900000095367432, "language": "en"}, {"identifier": "681af957-c9ea-49b7-aa16-bc6c47f51f97", "boundingBox": {"vertices": [{"x": 2044, "y": 1865}, {"x": 2278, "y": 1867}, {"x": 2278, "y": 1907}, {"x": 2044, "y": 1905}]}, "text": "ADVOCATE", "confidence": 0.9900000095367432, "language": "en"}, {"identifier": "71ff3748-a639-442e-96a8-1533d7fd1ff4", "boundingBox": {"vertices": [{"x": 2306, "y": 1868}, {"x": 2315, "y": 1868}, {"x": 2315, "y": 1907}, {"x": 2306, "y": 1907}]}, "text": ".", "confidence": 0.7599999904632568, "language": "en"}, {"identifier": "5a9fa3b9-3ae2-4374-961a-2df42ed1a674", "boundingBox": {"vertices": [{"x": 2304, "y": 1854}, {"x": 2322, "y": 1854}, {"x": 2322, "y": 1918}, {"x": 2304, "y": 1918}]}, "text": ".", "confidence": 0.47999998927116394, "language": "en"}, {"identifier": "403fa2dd-d248-4c2e-9a6e-800e01a07688", "boundingBox": {"vertices": [{"x": 1132, "y": 2038}, {"x": 1453, "y": 2039}, {"x": 1453, "y": 2079}, {"x": 1132, "y": 2078}]}, "text": "CERTIFICATE", "confidence": 0.9900000095367432, "language": "en"}, {"identifier": "7736fc54-6ff8-4e48-9a26-2b8fe47befe9", "boundingBox": {"vertices": [{"x": 1481, "y": 2040}, {"x": 1489, "y": 2040}, {"x": 1489, "y": 2079}, {"x": 1481, "y": 2079}]}, "text": ".", "confidence": 0.9900000095367432, "language": "en"}, {"identifier": "daf0f2ad-a519-4631-bc99-ee0b83542d7c", "boundingBox": {"vertices": [{"x": 802, "y": 2178}, {"x": 1069, "y": 2178}, {"x": 1069, "y": 2239}, {"x": 802, "y": 2239}]}, "text": "Certified", "confidence": 0.8500000238418579, "language": "en"}, {"identifier": "4e1aba17-bed4-4d8d-97f4-c8181f72fb06", "boundingBox": {"vertices": [{"x": 1106, "y": 2178}, {"x": 1221, "y": 2178}, {"x": 1221, "y": 2239}, {"x": 1106, "y": 2239}]}, "text": "that", "confidence": 0.9900000095367432, "language": "en"}, {"identifier": "c5bf28b4-233a-4603-be48-26572af4030c", "boundingBox": {"vertices": [{"x": 1256, "y": 2178}, {"x": 1279, "y": 2178}, {"x": 1279, "y": 2239}, {"x": 1256, "y": 2239}]}, "text": "I", "confidence": 0.9900000095367432, "language": "en"}, {"identifier": "22bd1ea3-0859-4c4f-a9d4-32a41fc3f117", "boundingBox": {"vertices": [{"x": 1314, "y": 2178}, {"x": 1435, "y": 2178}, {"x": 1435, "y": 2239}, {"x": 1314, "y": 2239}]}, "text": "have", "confidence": 0.9900000095367432, "language": "en"}, {"identifier": "a5805e88-6bd5-494e-8920-02c0ed3e1643", "boundingBox": {"vertices": [{"x": 1466, "y": 2178}, {"x": 1589, "y": 2178}, {"x": 1589, "y": 2239}, {"x": 1466, "y": 2239}]}, "text": "been", "confidence": 0.9900000095367432, "language": "en"}, {"identifier": "d3b96012-3983-4063-904b-a45dbe7f80d7", "boundingBox": {"vertices": [{"x": 1624, "y": 2178}, {"x": 1957, "y": 2178}, {"x": 1957, "y": 2239}, {"x": 1624, "y": 2239}]}, "text": "instructedst", "confidence": 0.9700000286102295, "language": "en"}, {"identifier": "c79b4cc4-13ea-4f23-8a51-7ba53acd9a64", "boundingBox": {"vertices": [{"x": 1986, "y": 2178}, {"x": 2047, "y": 2178}, {"x": 2047, "y": 2239}, {"x": 1986, "y": 2239}]}, "text": "by", "confidence": 0.8999999761581421, "language": "en"}, {"identifier": "bc4f2b2b-fe2b-4b98-adfd-ec53b6622440", "boundingBox": {"vertices": [{"x": 2082, "y": 2178}, {"x": 2169, "y": 2178}, {"x": 2169, "y": 2239}, {"x": 2082, "y": 2239}]}, "text": "the", "confidence": 0.8199999928474426, "language": "en"}, {"identifier": "00ee795c-2011-4e96-928b-6c7a6bb303bd", "boundingBox": {"vertices": [{"x": 556, "y": 2262}, {"x": 705, "y": 2262}, {"x": 705, "y": 2307}, {"x": 556, "y": 2307}]}, "text": "State", "confidence": 0.9900000095367432, "language": "en"}, {"identifier": "08745b6a-d953-43a5-8642-8000475c23e3", "boundingBox": {"vertices": [{"x": 738, "y": 2262}, {"x": 1043, "y": 2262}, {"x": 1043, "y": 2307}, {"x": 738, "y": 2307}]}, "text": "Government", "confidence": 0.9800000190734863, "language": "en"}, {"identifier": "e2e11d98-c8fa-4b65-a6e1-56b8eba84ed3", "boundingBox": {"vertices": [{"x": 1076, "y": 2262}, {"x": 1131, "y": 2262}, {"x": 1131, "y": 2307}, {"x": 1076, "y": 2307}]}, "text": "fo", "confidence": 0.9900000095367432, "language": "en"}, {"identifier": "1cc27cb1-0437-4d7f-864f-1e9755905ffe", "boundingBox": {"vertices": [{"x": 1166, "y": 2262}, {"x": 1281, "y": 2262}, {"x": 1281, "y": 2307}, {"x": 1166, "y": 2307}]}, "text": "file", "confidence": 0.9900000095367432, "language": "en"}, {"identifier": "7da90902-f355-4329-8f3d-d216f288c985", "boundingBox": {"vertices": [{"x": 1316, "y": 2262}, {"x": 1405, "y": 2262}, {"x": 1405, "y": 2307}, {"x": 1316, "y": 2307}]}, "text": "and", "confidence": 0.9900000095367432, "language": "en"}, {"identifier": "3be9b932-4697-4586-88da-bf3a175e843a", "boundingBox": {"vertices": [{"x": 1442, "y": 2262}, {"x": 1651, "y": 2262}, {"x": 1651, "y": 2307}, {"x": 1442, "y": 2307}]}, "text": "conduct", "confidence": 0.9900000095367432, "language": "en"}, {"identifier": "45d540f8-ca73-43bd-a730-7b6d8fbeeb36", "boundingBox": {"vertices": [{"x": 1684, "y": 2262}, {"x": 1797, "y": 2262}, {"x": 1797, "y": 2307}, {"x": 1684, "y": 2307}]}, "text": "this", "confidence": 0.9900000095367432, "language": "en"}, {"identifier": "04d8f4fc-84bc-4463-b3bd-1d268e64c0bc", "boundingBox": {"vertices": [{"x": 1836, "y": 2262}, {"x": 1953, "y": 2262}, {"x": 1953, "y": 2307}, {"x": 1836, "y": 2307}]}, "text": "case", "confidence": 0.9900000095367432, "language": "en"}, {"identifier": "b3dd072c-3528-4e15-ab58-110e02960664", "boundingBox": {"vertices": [{"x": 1964, "y": 2262}, {"x": 1977, "y": 2262}, {"x": 1977, "y": 2307}, {"x": 1964, "y": 2307}]}, "text": ".", "confidence": 0.9599999785423279, "language": "en"}, {"identifier": "2e50ce34-083c-43b4-9ecd-bc56eba092ff", "boundingBox": {"vertices": [{"x": 1056, "y": 2409}, {"x": 1063, "y": 2409}, {"x": 1063, "y": 2422}, {"x": 1056, "y": 2422}]}, "text": "2", "confidence": 0.3400000035762787, "language": "en"}, {"identifier": "7cfefb2b-03ad-4a71-afb7-7f200ef5931f", "boundingBox": {"vertices": [{"x": 1837, "y": 2302}, {"x": 2073, "y": 2299}, {"x": 2076, "y": 2523}, {"x": 1840, "y": 2526}]}, "text": "Emma", "confidence": 0.5, "language": "en"}, {"identifier": "37f6a912-88b9-4d44-9e11-849293d1fe40", "boundingBox": {"vertices": [{"x": 433, "y": 2457}, {"x": 436, "y": 2457}, {"x": 436, "y": 2468}, {"x": 433, "y": 2468}]}, "text": ".", "confidence": 0.05000000074505806, "language": "en"}, {"identifier": "c1411067-4d34-45c2-a9c7-60cbcced1a6f", "boundingBox": {"vertices": [{"x": 1712, "y": 2523}, {"x": 2015, "y": 2523}, {"x": 2015, "y": 2589}, {"x": 1712, "y": 2589}]}, "text": "GOVERNMENT", "confidence": 0.9900000095367432, "language": "en"}, {"identifier": "ea1cc39e-668f-466c-b299-25a8162e8579", "boundingBox": {"vertices": [{"x": 2044, "y": 2523}, {"x": 2282, "y": 2523}, {"x": 2282, "y": 2589}, {"x": 2044, "y": 2589}]}, "text": "ADVOCATE", "confidence": 0.9900000095367432, "language": "en"}, {"identifier": "1ff0c7f7-d276-4914-8bec-1cc1e41046e2", "boundingBox": {"vertices": [{"x": 2302, "y": 2523}, {"x": 2315, "y": 2523}, {"x": 2315, "y": 2589}, {"x": 2302, "y": 2589}]}, "text": ".", "confidence": 0.949999988079071, "language": "en"}, {"identifier": "72365e89-6576-438c-ac6a-2a6faaf8c866", "boundingBox": {"vertices": [{"x": 2157, "y": 2949}, {"x": 2160, "y": 2949}, {"x": 2160, "y": 2963}, {"x": 2157, "y": 2963}]}, "text": "1", "confidence": 0.4000000059604645, "language": "en"}], "vertices": [{"x": 0, "y": 0}, {"x": 2481, "y": 0}, {"x": 2481, "y": 3508}, {"x": 0, "y": 3508}]}]}]}}